bento/__init__.py
bento/_version.py
bento/bank.py
bento/banks_v1.py
bento/bento.py
bento/components.py
bento/graph.py
bento/grid.py
bento/launcher.py
bento/named_themes.py
bento/resources.py
bento/schema.py
bento/style.py
bento/util.py
bento/assets/geojson_us_counties.json
bento/assets/geojson_us_states.json
bento/assets/geojson_world.json
bento/assets/sample_covid_data.csv
bento/assets/sample_mars_data.csv
bento/assets/sample_oilngas_data.csv
bento/assets/sample_stock_data.csv
bento/assets/world_country_reference.csv
bento/banks/__init__.py
bento/banks/analytics_set.py
bento/banks/date_control.py
bento/banks/graph.py
bento/banks/selector.py
bento/common/__init__.py
bento/common/codeutil.py
bento/common/datautil.py
bento/common/dictutil.py
bento/common/logger.py
bento/common/logutil.py
bento/common/util.py
bento/dashboards/__init__.py
bento/dashboards/demo.py
bento/dashboards/simple.py
bento/sample_data/__init__.py
bento/sample_data/covid.py
bento/sample_data/mars.py
bento/sample_data/oil.py
bento/sample_data/stock.py
bento/templates/baseline.css.j2
bento/templates/bento_v1.py.j2
bento/templates/theme.css.j2
bento_dash-0.0.9.dist-info/LICENSE
bento_dash-0.0.9.dist-info/METADATA
bento_dash-0.0.9.dist-info/WHEEL
bento_dash-0.0.9.dist-info/entry_points.txt
bento_dash-0.0.9.dist-info/top_level.txt
bento_dash-0.0.9.dist-info/RECORD
