Metadata-Version: 2.1
Name: bento-dash
Version: 0.0.9
Summary: Create Plotly Dash apps via templates
Home-page: https://github.com/dereklarson/bento
Author: Derek Larson
Author-email: larson.derek.a@gmail.com
License: MIT
Platform: UNKNOWN
Classifier: Development Status :: 1 - Planning
Classifier: Intended Audience :: Developers
Classifier: Intended Audience :: Education
Classifier: Intended Audience :: Science/Research
Classifier: License :: OSI Approved :: MIT License
Classifier: Programming Language :: Python :: 3
Classifier: Programming Language :: Python :: 3.7
Classifier: Topic :: Scientific/Engineering :: Visualization
Requires-Python: >=3.7
Requires-Dist: black
Requires-Dist: cerberus
Requires-Dist: dash
Requires-Dist: gunicorn
Requires-Dist: pandas
Requires-Dist: prettyprinter
Requires-Dist: pyyaml
Provides-Extra: dev
Requires-Dist: pytest ; extra == 'dev'
Requires-Dist: pytest-cov ; extra == 'dev'
Requires-Dist: sphinx (>=3.2) ; extra == 'dev'
Requires-Dist: sphinx-rtd-theme ; extra == 'dev'
